nanomix-0.2.0.dist-info/METADATA
nanomix-0.2.0.dist-info/WHEEL
nanomix-0.2.0.dist-info/entry_points.txt
nanomix-0.2.0.dist-info/license_files/LICENSE
nanomix/plot.py
nanomix/atlas.py
nanomix/tests/test_load_atlas.py
nanomix/tests/test_deconvolute.py
nanomix/tests/test_mmse.py
nanomix/tests/test_simulate.py
nanomix/tests/test_data/test_sigma.tsv
nanomix/tests/test_data/39Bisulfite.tsv
nanomix/tests/test_data/test_methylome.tsv
nanomix/tests/test_data/39Bisulfite-endothelial.tsv
nanomix/tests/test_data/test_atlas.tsv
nanomix/tests/test_evaluate.py
nanomix/tests/test_assign.py
nanomix/main.py
nanomix/run_tests.py
nanomix/__init__.py
nanomix/functions.py
nanomix/models.py
nanomix/tools.py
nanomix/_nanomix.cpython-39-x86_64-linux-gnu.so
nanomix-0.2.0.dist-info/RECORD
